LICENSE
README.md
pyproject.toml
sdkmanager.py
setup.cfg
setup.py
sdkmanager.egg-info/PKG-INFO
sdkmanager.egg-info/SOURCES.txt
sdkmanager.egg-info/dependency_links.txt
sdkmanager.egg-info/entry_points.txt
sdkmanager.egg-info/requires.txt
sdkmanager.egg-info/top_level.txt